temper.py
temper_py-0.0.4.dist-info/LICENSE
temper_py-0.0.4.dist-info/METADATA
temper_py-0.0.4.dist-info/WHEEL
temper_py-0.0.4.dist-info/entry_points.txt
temper_py-0.0.4.dist-info/top_level.txt
temper_py-0.0.4.dist-info/RECORD
