Metadata-Version: 2.1
Name: temper-py
Version: 0.0.4
Summary: Reads temperature data from misc. "TEMPer" devices with minimal dependencies
Home-page: https://github.com/ccwienk/temper
Author: urwen
Classifier: Programming Language :: Python :: 3
Classifier: License :: OSI Approved :: MIT License
Classifier: Operating System :: POSIX :: Linux
License-File: LICENSE
Requires-Dist: pyserial
